personal.py
personal-0.1.1.dist-info/DESCRIPTION.rst
personal-0.1.1.dist-info/METADATA
personal-0.1.1.dist-info/RECORD
personal-0.1.1.dist-info/WHEEL
personal-0.1.1.dist-info/entry_points.txt
personal-0.1.1.dist-info/metadata.json
personal-0.1.1.dist-info/top_level.txt
