Metadata-Version: 2.0
Name: personal
Version: 0.1.1
Summary: Easy, secure self notification via email and sms, using smtplib and twilio
Home-page: https://github.com/tommilligan/personal
Author: Tom Milligan
Author-email: code@tommilligan.net
License: GPL
Keywords: personal automation automatic notification email sms text secure
Platform: UNKNOWN
Classifier: Development Status :: 4 - Beta
Classifier: Intended Audience :: Developers
Classifier: Operating System :: OS Independent
Classifier: Topic :: Software Development :: Libraries :: Python Modules
Classifier: License :: OSI Approved :: GNU General Public License v2 (GPLv2)
Classifier: Natural Language :: English
Classifier: Programming Language :: Python :: 3
Requires-Dist: pycrypto
Requires-Dist: twilio
